timeslime/__init__.py
timeslime/__main__.py
timeslime/__version__.py
timeslime/models.py
timeslime/services/__init__.py
timeslime/services/configuration_service.py
timeslime/services/report_service.py
timeslime/services/synchronize_service.py
timeslime/services/time_service.py
timeslime-2.3.0.dist-info/METADATA
timeslime-2.3.0.dist-info/WHEEL
timeslime-2.3.0.dist-info/entry_points.txt
timeslime-2.3.0.dist-info/RECORD
