Metadata-Version: 2.1
Name: timeslime
Version: 2.3.0
Summary: ⌚ This is timeslime! Have fun tracking your time ⌚
Project-URL: Source Code, https://gitlab.com/lookslikematrix/timeslime
Author-email: Christian Decker <christian.decker@lookslikematrix.com>
License-Expression: MIT
Classifier: Operating System :: OS Independent
Classifier: Programming Language :: Python :: 3
Requires-Python: >=3.11
Requires-Dist: click==8.1.6
Requires-Dist: peewee==3.17.0
Requires-Dist: requests==2.31.0
Requires-Dist: rich==13.5.1
